ai_explain/__init__.py
ai_explain-0.1.0.dist-info/entry_points.txt
ai_explain-0.1.0.dist-info/licenses/LICENSE
ai_explain-0.1.0.dist-info/WHEEL
ai_explain-0.1.0.dist-info/METADATA
ai_explain-0.1.0.dist-info/RECORD
