Metadata-Version: 2.4
Name: ai-explain
Version: 0.1.0
Summary: AI-powered command-line tool for instant explanations of code and terminal commands.
Author-email: Kyle O'Malley <j.kyle.omalley@gmail.com>
Requires-Python: >=3.10
License-File: LICENSE
Requires-Dist: click>=8.2.0
Requires-Dist: google-genai>=1.15.0
